xgbordinal/__init__.py
xgbordinal/utils.py
xgbordinal/xgbordinal.py
xgbordinal-1.0.1.dist-info/METADATA
xgbordinal-1.0.1.dist-info/WHEEL
xgbordinal-1.0.1.dist-info/licenses/LICENSE.txt
xgbordinal-1.0.1.dist-info/RECORD
