Metadata-Version: 2.4
Name: xgbordinal
Version: 1.0.1
Summary: XGBOrdinal: An XGBoost Extension for Ordinal Data
Project-URL: Homepage, https://github.com/digital-medicine/XGBOrdinal
Project-URL: Repository, https://github.com/digital-medicine/XGBOrdinal
Project-URL: Issues, https://github.com/digital-medicine/XGBOrdinal/issues
Author-email: Fabian Kahl <fabian.kahl@ukbonn.de>
License: Software License
License-File: LICENSE.txt
Classifier: License :: Other/Proprietary License
Classifier: Operating System :: OS Independent
Classifier: Programming Language :: Python :: 3
Requires-Python: >=3.10
Requires-Dist: pandas>=2.0.3
Requires-Dist: scikit-learn>=1.3.0
Requires-Dist: xgboost>=2.0.3
